erede/Additional.py
erede/Address.py
erede/Antifraud.py
erede/Authorization.py
erede/Capture.py
erede/Cart.py
erede/Consumer.py
erede/Document.py
erede/Environment.py
erede/Flight.py
erede/Iata.py
erede/Item.py
erede/Passenger.py
erede/Phone.py
erede/RedeError.py
erede/RedeSerializable.py
erede/Refund.py
erede/Store.py
erede/SubMerchant.py
erede/ThreeDSecure.py
erede/Transaction.py
erede/Url.py
erede/__init__.py
erede/eRede.py
erede/service/CancelTransactionService.py
erede/service/CaptureTransactionService.py
erede/service/CreateTransactionService.py
erede/service/GetTransactionService.py
erede/service/TransactionService.py
erede/service/__init__.py
rede_payments-1.0.0.dist-info/LICENSE
rede_payments-1.0.0.dist-info/METADATA
rede_payments-1.0.0.dist-info/WHEEL
rede_payments-1.0.0.dist-info/top_level.txt
rede_payments-1.0.0.dist-info/RECORD
