Metadata-Version: 2.1
Name: rede-payments
Version: 1.0.0
Summary: A package to handle rede payments api
Home-page: https://github.com/darleisantossoares/erede-python
Author: Darlei Soares
Author-email: darleisantossoares@gmail.com
License: UNKNOWN
Platform: UNKNOWN
Classifier: Programming Language :: Python :: 3
Classifier: License :: OSI Approved :: MIT License
Classifier: Operating System :: OS Independent
